{
  "id": "signup",
  "route": "/signup/",
  "locale": "en",
  "status": "published",
  "template": "standard-approved-v1",
  "editorMode": "approved_blocks",
  "seo": {
    "title": "Sign Up for Wink | Hotels, Partners and Platforms",
    "metaDescription": "Start a Wink account for hotel direct demand, Partner storefronts, Booking Engine paths, Traveliko participation, or platform access.",
    "canonical": "https://www.wink.travel/signup/",
    "robots": "index,follow",
    "ogTitle": "Start with the path that fits you.",
    "ogDescription": "Start a Wink account for hotel direct demand, Partner storefronts, Booking Engine paths, Traveliko participation, or platform access.",
    "ogImage": "https://www.wink.travel/assets/facebook-post.png"
  },
  "content": {
    "h1": "Start with the path that fits you.",
    "summary": "Start a Wink account for hotel direct demand, Partner storefronts, Booking Engine paths, Traveliko participation, or platform access.",
    "blocks": [
      {
        "id": "signup-hero",
        "type": "hero",
        "editable": true,
        "fields": {
          "kicker": "Sign up",
          "h1": "Start with the path that fits you.",
          "lead": "Start a Wink account for hotel direct demand, Partner storefronts, Booking Engine paths, Traveliko participation, or platform access.",
          "supportLine": "",
          "routeChip": "",
          "actions": [
            {
              "label": "Request a demo",
              "href": "/demo/",
              "className": "btn btn-orange"
            },
            {
              "label": "Get started",
              "href": "/signup/",
              "className": "btn btn-white"
            }
          ],
          "visuals": []
        }
      },
      {
        "id": "signup-answer",
        "type": "direct_answer",
        "editable": true,
        "fields": {
          "kicker": "Direct answer",
          "titleId": "signup-answer-title",
          "heading": "Start with the path that fits you.",
          "body": "Start a Wink account for hotel direct demand, Partner storefronts, Booking Engine paths, Traveliko participation, or platform access.",
          "link": {
            "label": "Request a demo",
            "href": "/demo/",
            "className": "btn btn-orange"
          }
        }
      },
      {
        "id": "signup-cards",
        "type": "card_grid",
        "editable": true,
        "fields": {
          "sectionClass": "section",
          "titleId": "signup-cards-title",
          "kicker": "What you can do here",
          "heading": "Choose the next step that fits your role.",
          "body": "Start a Wink account for hotel direct demand, Partner storefronts, Booking Engine paths, Traveliko participation, or platform access.",
          "gridClass": "three-grid",
          "cards": [
            {
              "title": "Hotel team",
              "body": "Set up property content, rates, packages, and Booking Engine paths.",
              "link": {
                "label": "Hotel team",
                "href": "../hotels/"
              }
            },
            {
              "title": "Partner",
              "body": "Create bookable recommendations and storefront paths around approved hotel inventory.",
              "link": {
                "label": "Partner",
                "href": "../partners/"
              }
            },
            {
              "title": "Developer",
              "body": "Review API concepts and prepare a platform or app integration.",
              "link": {
                "label": "Developer",
                "href": "../developers/docs/"
              }
            }
          ]
        }
      },
      {
        "id": "signup-faq",
        "type": "faq",
        "editable": true,
        "fields": {
          "titleId": "signup-faq-title",
          "kicker": "FAQ",
          "heading": "Useful answers before you continue.",
          "items": [
            {
              "question": "Who can sign up for Wink?",
              "answer": "Hotels, Partners, and platform teams can start a Wink signup path. The setup route depends on the role."
            },
            {
              "question": "Should hotels request a demo or sign up?",
              "answer": "Hotels can sign up when they are ready to start setup. A demo is better when the team wants to discuss channel strategy first."
            },
            {
              "question": "Do Partners use the same setup path as hotels?",
              "answer": "No. Partners need a demand-side path focused on bookable assets, storefronts, attribution, and commercial terms."
            }
          ]
        }
      },
      {
        "id": "signup-cta",
        "type": "form_intro",
        "editable": true,
        "fields": {
          "titleId": "signup-cta-title",
          "kicker": "Next step",
          "heading": "Ready to make hotel demand bookable?",
          "body": "Start with the route that matches your team, then move into a focused demo or sign-up flow.",
          "actions": [
            {
              "label": "Request a demo",
              "href": "/demo/",
              "className": "btn btn-orange"
            },
            {
              "label": "Get started",
              "href": "/signup/",
              "className": "btn btn-white"
            }
          ]
        }
      }
    ]
  },
  "analysis": {
    "schemaTypes": [
      "Answer",
      "BreadcrumbList",
      "FAQPage",
      "ListItem",
      "Organization",
      "Question",
      "WebPage"
    ],
    "faqQuestions": [
      "Who can sign up for Wink?",
      "Should hotels request a demo or sign up?",
      "Do Partners use the same setup path as hotels?"
    ],
    "imageSources": [
      "../assets/wink-logo-purple.png",
      "../assets/wink-logo-white.png"
    ],
    "legacyHtmlBytes": 12054
  },
  "updatedAt": "2026-05-28T06:21:03.145Z",
  "updatedBy": "system:approved-block-conversion"
}
